beepbeep_txflowutils/auth/__init__.py
beepbeep_txflowutils/auth/info_schema.py
beepbeep_txflowutils/auth/service_account.py
beepbeep_txflowutils/github_source/__init__.py
beepbeep_txflowutils/github_source/github_source.py
beepbeep_txflowutils/secrets/__init__.py
beepbeep_txflowutils/secrets/config.py
beepbeep_txflowutils/secrets/config_setting.py
beepbeep_txflowutils/secrets/service_account_credentials/__init__.py
beepbeep_txflowutils/utils/__init__.py
beepbeep_txflowutils/utils/utils.py
bqtxflowutils_2-0.0.6.dist-info/LICENSE
bqtxflowutils_2-0.0.6.dist-info/METADATA
bqtxflowutils_2-0.0.6.dist-info/WHEEL
bqtxflowutils_2-0.0.6.dist-info/top_level.txt
bqtxflowutils_2-0.0.6.dist-info/RECORD
