Metadata-Version: 2.1
Name: bqtxflowutils-2
Version: 0.0.6
Summary: Sync data transformation information from BigQuery to GitHub and create a dynamic Markdown documantation.
Home-page: https://github.com/beepbeeptechnology/sync_from_bigquery_to_github
Author: Beepbeep Technology
Author-email: contact@beepbeep.technology
License: UNKNOWN
Platform: UNKNOWN
Classifier: Programming Language :: Python :: 3
Classifier: License :: OSI Approved :: MIT License
Classifier: Operating System :: OS Independent
Requires-Python: >=3.6
License-File: LICENSE
Requires-Dist: streamlit (==0.83.0)
Requires-Dist: mdutils
Requires-Dist: google-cloud (==0.34.0)
Requires-Dist: google-cloud-bigquery (==2.20.0)
